[
    {
        "id": 1,
        "title": "【新品上市】GLACITEK 全新鍵盤系列即將上市！",
        "content": "我們即將推出全新旗艦級鍵盤，搭載磁軸技術與人體工學設計，敬請期待！",
        "date": "2025/05/15"
    },
    {
        "id": 2,
        "title": "【系統更新】官網將於 5/12 進行維護作業",
        "content": "為提供更佳的購物體驗，網站預計於 5/12凌晨 2:00~4:00 進行維護",
        "date": "2025/05/12"
    },
    {
        "id": 3,
        "title": "【系統更新】維修中心服務升級公告",
        "content": "自六月起，新增多處維修據點，提供快速檢測與即時維修服務。",
        "date": "2025/04/30"
    },
    {
        "id": 4,
        "title": "【限時活動】春季促銷活動即將登場",
        "content": "多項熱銷商品限時折扣，數量有限，售完為止！",
        "date": "2025/04/20"
    },
    {
        "id": 5,
        "title": "【新品上市】GLACITEK 專業電競滑鼠強勢登場！",
        "content": "全新滑鼠系列搭載高精度感測器與可調整重量模組，打造專屬你的極致操控手感！",
        "date": "2025/06/01"
    },
    {
        "id": 6,
        "title": "【新品預告】GLACITEK 麥克風系列 即將公開",
        "content": "為創作者打造的專業錄音解決方案，支援多種指向模式與即時監聽功能，敬請期待！",
        "date": "2025/06/10"
    },
    {
        "id": 7,
        "title": "【【全新體驗】GLACITEK 顯示器系列 開創視覺新標準！",
        "content": "採用高速刷新率與低藍光護眼技術，帶來沉浸感十足的遊戲與工作視野。",
        "date": "2025/06/20"
    },
    {
        "id": 8,
        "title": "【限量開賣】GLACITEK 多功能 HUB 問世！",
        "content": "支援多裝置擴充與高速傳輸，讓桌面連接從未如此流暢與俐落。",
        "date": "2025/06/25"
    },
    {
        "id": 9,
        "title": "【產品升級】GLACITEK 人體工學滑鼠墊 改版上市",
        "content": "提升舒適支撐與散熱功能，長時間使用依然輕鬆無負擔。",
        "date": "2025/07/05"
    }
]
